joinem/__init__.py
joinem/__main__.py
joinem/_dataframe_cli.py
joinem-0.11.1.dist-info/licenses/LICENSE
joinem-0.11.1.dist-info/METADATA
joinem-0.11.1.dist-info/WHEEL
joinem-0.11.1.dist-info/entry_points.txt
joinem-0.11.1.dist-info/top_level.txt
joinem-0.11.1.dist-info/RECORD
