Metadata-Version: 2.4
Name: joinem
Version: 0.11.1
Summary: CLI for fast, flexbile concatenation of tabular data using Polars.
Author-email: Matthew Andres Moreno <m.more500@gmail.com>
License: MIT license
Project-URL: homepage, https://github.com/mmore500/joinem
Project-URL: documentation, https://github.com/mmore500/joinem
Project-URL: repository, https://github.com/mmore500/joinem
Project-URL: tracker, https://github.com/mmore500/joinem/issues
Keywords: polars,data processing,CSV,parquet,data science
Classifier: Development Status :: 3 - Alpha
Classifier: Intended Audience :: Developers
Classifier: Topic :: Software Development :: Libraries :: Python Modules
Classifier: License :: OSI Approved :: MIT License
Classifier: Programming Language :: Python :: 3
Classifier: Programming Language :: Python :: 3.8
Classifier: Programming Language :: Python :: 3.9
Classifier: Programming Language :: Python :: 3.10
Classifier: Programming Language :: Python :: 3.11
Classifier: Programming Language :: Python :: 3.12
Requires-Python: >=3.9
License-File: LICENSE
Requires-Dist: polars>=1.26.0
Requires-Dist: tqdm
Provides-Extra: dev
Requires-Dist: black==22.10.0; extra == "dev"
Requires-Dist: bump2version==1.0.1; extra == "dev"
Requires-Dist: isort==5.12.0; extra == "dev"
Requires-Dist: pip-tools==7.3.0; extra == "dev"
Requires-Dist: ruff==0.1.11; extra == "dev"
Dynamic: license-file
